github_mcp_server/__init__.py
github_mcp_server/server.py
github_mcp_server/config/__init__.py
github_mcp_server/config/defaults.py
github_mcp_server/tools/__init__.py
github_mcp_server/tools/batch_operations.py
github_mcp_server/tools/ci.py
github_mcp_server/tools/issues.py
github_mcp_server/tools/milestones.py
github_mcp_server/tools/pulls.py
github_mcp_server/utils/__init__.py
github_mcp_server/utils/errors.py
github_mcp_server/utils/formatter.py
github_mcp_server/utils/github_client.py
github_mcp_server/utils/types.py
rriesco_mcp_github-0.1.3.dist-info/METADATA
rriesco_mcp_github-0.1.3.dist-info/WHEEL
rriesco_mcp_github-0.1.3.dist-info/entry_points.txt
rriesco_mcp_github-0.1.3.dist-info/licenses/LICENSE
rriesco_mcp_github-0.1.3.dist-info/RECORD
