Metadata-Version: 2.4
Name: rriesco-mcp-github
Version: 0.1.3
Summary: MCP server for GitHub API operations - issues, PRs, CI, milestones
Project-URL: Homepage, https://github.com/rriesco/github-mcp-server
Project-URL: Repository, https://github.com/rriesco/github-mcp-server
Project-URL: Issues, https://github.com/rriesco/github-mcp-server/issues
Author-email: Rafael Riesco <rriesco@users.noreply.github.com>
License: MIT
License-File: LICENSE
Keywords: anthropic,api,automation,claude,github,mcp
Classifier: Development Status :: 4 - Beta
Classifier: Intended Audience :: Developers
Classifier: License :: OSI Approved :: MIT License
Classifier: Programming Language :: Python :: 3
Classifier: Programming Language :: Python :: 3.10
Classifier: Programming Language :: Python :: 3.11
Classifier: Programming Language :: Python :: 3.12
Classifier: Topic :: Software Development :: Libraries :: Python Modules
Requires-Python: >=3.10
Requires-Dist: mcp[cli]>=0.9.0
Requires-Dist: pygithub>=2.1.0
Requires-Dist: python-dotenv>=1.0.0
Provides-Extra: dev
Requires-Dist: mypy>=1.0.0; extra == 'dev'
Requires-Dist: pytest-asyncio>=0.21.0; extra == 'dev'
Requires-Dist: pytest-cov>=4.0.0; extra == 'dev'
Requires-Dist: pytest>=7.0.0; extra == 'dev'
